mm_wlan/__init__.py
mm_wlan/mm_wlan.py
mm_wlan-0.5.dist-info/LICENSE.txt
mm_wlan-0.5.dist-info/METADATA
mm_wlan-0.5.dist-info/WHEEL
mm_wlan-0.5.dist-info/top_level.txt
mm_wlan-0.5.dist-info/RECORD
