Metadata-Version: 2.1
Name: mm_wlan
Version: 0.5
Summary: WLAN Connection functions in MicroPython
Home-page: https://github.com/monkmakes/mm_wlan
Download-URL: https://github.com/monkmakes/mm_wlan/archive/refs/tags/v_02.tar.gz
Author: Simon Monk and José Antonio Vacas
Author-email: simon@monkmakes.com
License: MIT
Keywords: WLAN,micropython,webserver
Classifier: Development Status :: 3 - Alpha
Classifier: Intended Audience :: Developers
Classifier: Topic :: Software Development :: Build Tools
Classifier: Programming Language :: Python :: Implementation :: MicroPython
Classifier: License :: OSI Approved :: MIT License
Classifier: Programming Language :: Python :: 3
License-File: LICENSE.txt
